fluctuate/__init__.py
fluctuate/cli.py
fluctuate/migrations.py
fluctuate/secrets_manager.py
fluctuate-4.0.1.dist-info/LICENSE
fluctuate-4.0.1.dist-info/METADATA
fluctuate-4.0.1.dist-info/WHEEL
fluctuate-4.0.1.dist-info/entry_points.txt
fluctuate-4.0.1.dist-info/RECORD
