Metadata-Version: 2.1
Name: fluctuate
Version: 4.0.1
Summary: A simple migration utility for Fauna DB.
Home-page: https://gitlab.com/munipal-oss/fluctuate
License: MIT
Author: Ryan Causey
Author-email: ryan.causey@munipal.io
Requires-Python: >=3.9,<4.0
Classifier: License :: OSI Approved :: MIT License
Classifier: Programming Language :: Python :: 3
Classifier: Programming Language :: Python :: 3.9
Classifier: Programming Language :: Python :: 3.10
Classifier: Programming Language :: Python :: 3.11
Classifier: Programming Language :: Python :: 3.12
Classifier: Programming Language :: Python :: 3.13
Provides-Extra: aws-secrets-manager
Requires-Dist: boto3[crt] (>=1.26.128,<2.0.0) ; extra == "aws-secrets-manager"
Requires-Dist: click (>=8.1.3,<9.0.0)
Requires-Dist: click-log (>=0.4.0,<0.5.0)
Requires-Dist: cloup (>=3.0.0,<4.0.0)
Requires-Dist: fauna (>=2.0.0,<3.0.0)
Requires-Dist: faunadb (>=4.3.1,<5.0.0)
Requires-Dist: tenacity (>=9.0.0,<10.0.0)
Project-URL: Repository, https://gitlab.com/munipal-oss/fluctuate
